{
":sunny:" : ["sunny","BLACK SUN WITH RAYS"],
":umbrella:" : ["umbrella","UMBRELLA WITH RAIN DROPS"],
":cloud:" : ["cloud"],
":snowflake:" : ["snowflake"],
":snowman:" : ["snowman","SNOWMAN WITHOUT SNOW"],
":zap:" : ["zap","HIGH VOLTAGE SIGN"],
":cyclone:" : ["cyclone","typhoon", "hurricane"],
":foggy:" : ["fog", "foggy"],
":ocean:" : ["ocean","WATER WAVE"],
":cat:" : ["cat","CAT FACE"],
":dog:" : ["dog","DOG FACE"],
":mouse:" : ["mouse","MOUSE FACE"],
":hamster:" : ["hamster","HAMSTER FACE"],
":rabbit:" : ["rabbit","RABBIT FACE"],
":wolf:" : ["wolf","WOLF FACE"],
":frog:" : ["frog","FROG FACE"],
":tiger:" : ["tiger","TIGER FACE"],
":koala:" : ["koala"],
":bear:" : ["bear","BEAR FACE"],
":pig:" : ["pig","PIG FACE"],
":pig_nose:" : ["pig nose"],
":cow:" : ["cow","COW FACE"],
":boar:" : ["boar"],
":monkey_face:" : ["monkey face"],
":monkey:" : ["monkey"],
":horse:" : ["horse","HORSE FACE"],
":racehorse:" : ["racehorse","HORSE"],
":camel:" : ["camel","BACTRIAN CAMEL","humps"],
":sheep:" : ["sheep"],
":elephant:" : ["elephant"],
":panda_face:" : ["panda face"],
":snake:" : ["snake"],
":bird:" : ["bird"],
":baby_chick:" : ["baby chick", "chick"],
":hatched_chick:" : ["hatched chick","FRONT-FACING BABY CHICK", "CHICK"],
":hatching_chick:" : ["hatching chick"],
":chicken:" : ["chicken"],
":penguin:" : ["penguin"],
":turtle:" : ["turtle"],
":bug:" : ["bug"],
":honeybee:" : ["honeybee"],
":ant:" : ["ant"],
":beetle:" : ["beetle","LADY BEETLE","ladybird", "ladybug", "coccinellids"], 
":snail:" : ["snail"],
":octopus:" : ["octopus"],
":tropical_fish:" : ["tropical fish"],
":fish:" : ["fish"],
":whale:" : ["whale","SPOUTING WHALE"],
":whale2:" : ["whale2","WHALE"],
":dolphin:" : ["dolphin"],
":cow2:" : ["cow2","COW"],
":ram:" : ["ram"],
":rat:" : ["rat"],
":water_buffalo:" : ["water buffalo"],
":tiger2:" : ["tiger2","TIGER"],
":rabbit2:" : ["rabbit2","RABBIT"],
":dragon:" : ["dragon"],
":goat:" : ["goat"],
":rooster:" : ["rooster"],
":dog2:" : ["dog2","DOG"],
":pig2:" : ["pig2","PIG"],
":mouse2:" : ["mouse2","MOUSE"],
":ox:" : ["ox"],
":dragon_face:" : ["dragon face"],
":blowfish:" : ["blowfish"],
":crocodile:" : ["crocodile"],
":dromedary_camel:" : ["dromedary camel","hump"],
":leopard:" : ["leopard"],
":cat2:" : ["cat2","CAT"],
":poodle:" : ["poodle"],
":paw_prints:" : ["paw prints"],
":bouquet:" : ["bouquet"],
":cherry_blossom:" : ["cherry blossom"],
":tulip:" : ["tulip"],
":four_leaf_clover:" : ["four leaf clover"],
":rose:" : ["rose"],
":sunflower:" : ["sunflower"],
":hibiscus:" : ["hibiscus"],
":maple_leaf:" : ["maple leaf"],
":leaves:" : ["leaves","LEAF FLUTTERING IN WIND"],
":fallen_leaf:" : ["fallen leaf"],
":herb:" : ["herb"],
":mushroom:" : ["mushroom"],
":cactus:" : ["cactus"],
":palm_tree:" : ["palm tree"],
":evergreen_tree:" : ["evergreen tree"],
":deciduous_tree:" : ["deciduous tree"],
":chestnut:" : ["chestnut"],
":seedling:" : ["seedling"],
":blossom:" : ["blossom","daisy"],
":ear_of_rice:" : ["ear of rice"],
":shell:" : ["shell","SPIRAL SHELL"],
":globe_with_meridians:" : ["globe with meridians","international","world clocks","time zone"], 
":sun_with_face:" : ["sun with face"],
":full_moon_with_face:" : ["full moon with face"],
":new_moon_with_face:" : ["new moon with face"],
":new_moon:" : ["new moon","NEW MOON SYMBOL"],
":waxing_crescent_moon:" : ["waxing crescent moon","WAXING CRESCENT MOON SYMBOL"],
":first_quarter_moon:" : ["first quarter moon","FIRST QUARTER MOON SYMBOL","half moon"],
":waxing_gibbous_moon:" : ["waxing gibbous moon","WAXING GIBBOUS MOON SYMBOL","waxing moon"],
":full_moon:" : ["full moon","FULL MOON SYMBOL"],
":waning_gibbous_moon:" : ["waning gibbous moon","WAINING GIBBOUS MOON SYMBOL"],
":last_quarter_moon:" : ["last quarter moon","LAST QUARTER MOON SYMBOL"],
":waning_crescent_moon:" : ["waning crescent moon","WANING CRESCENT MOON SYMBOL"],
":last_quarter_moon_with_face:" : ["last quarter moon with face"],
":first_quarter_moon_with_face:" : ["first quarter moon with face"],
":moon:" : ["moon","CRESCENT MOON", "first quarter moon", "last quarter moon", "moon", "quarter moon"],
":earth_africa:" : ["earth africa","EARTH GLOBE EUROPE-AFRICA"],
":earth_americas:" : ["earth americas","EARTH GLOBE AMERICAS"],
":earth_asia:" : ["earth asia","EARTH GLOBE ASIA-AUSTRALIA"],
":volcano:" : ["volcano"],
":milky_way:" : ["milky way"],
":partly_sunny:" : ["partly sunny","SUN BEHIND CLOUD"],
":bamboo:" : ["bamboo","PINE DECORATION", "japanese new year"], 
":gift_heart:" : ["gift heart","HEART WITH RIBBON"],
":dolls:" : ["dolls","JAPANESE DOLLS", "doll", "Hinamatsuri"], 
":gift_heart:" : ["gift heart","HEART WITH RIBBON"],
":school_satchel:" : ["school satchel","Japanese school entrance ceremony", "japanese school"],
":mortar_board:" : ["mortar board","GRADUATION CAP", "graduation ceremony", "graduation"],
":flags:" : ["flags","CARP STREAMER"],
":fireworks:" : ["fireworks"],
":sparkler:" : ["sparkler","FIREWORK SPARKLER"],
":wind_chime:" : ["wind chime"],
":rice_scene:" : ["rice scene","MOON VIEWING CEREMONY", "Otsukimi", "harvest"],
":jack_o_lantern:" : ["jack o lantern","JACK-O-LANTERN","Halloween"],
":ghost:" : ["ghost"],
":santa:" : ["santa","FATHER CHRISTMAS", "Santa Claus", "Santa"], 
":8ball:" : ["8ball"],
":alarm_clock:" : ["alarm clock"],
":apple:" : ["apple"],
":art:" : ["art"],
":baby_bottle:" : ["baby bottle"],
":balloon:" : ["balloon"],
":banana:" : ["banana"],
":bar_chart:" : ["bar chart"],
":baseball:" : ["baseball"],
":basketball:" : ["basketball"],
":bath:" : ["bath"],
":bathtub:" : ["bathtub"],
":battery:" : ["battery"],
":beer:" : ["beer"],
":beers:" : ["beers"],
":bell:" : ["bell"],
":bento:" : ["bento"],
":bicyclist:" : ["bicyclist"],
":bikini:" : ["bikini"],
":birthday:" : ["birthday"],
":black_joker:" : ["black joker"],
":black_nib:" : ["black nib"],
":blue_book:" : ["blue book"],
":bomb:" : ["bomb"],
":bookmark:" : ["bookmark"],
":bookmark_tabs:" : ["bookmark tabs"],
":books:" : ["books"],
":boot:" : ["boot"],
":bowling:" : ["bowling"],
":bread:" : ["bread"],
":briefcase:" : ["briefcase"],
":bulb:" : ["bulb"],
":cake:" : ["cake"],
":calendar:" : ["calendar"],
":calling:" : ["calling"],
":camera:" : ["camera"],
":candy:" : ["candy"],
":card_index:" : ["card index"],
":cd:" : ["cd"],
":chart_with_downwards_trend:" : ["chart with downwards trend"],
":chart_with_upwards_trend:" : ["chart with upwards trend"],
":cherries:" : ["cherries"],
":chocolate_bar:" : ["chocolate bar"],
":christmas_tree:" : ["christmas tree"],
":clapper:" : ["clapper"],
":clipboard:" : ["clipboard"],
":closed_book:" : ["closed book"],
":closed_lock_with_key:" : ["closed lock with key"],
":closed_umbrella:" : ["closed umbrella"],
":clubs:" : ["clubs"],
":cocktail:" : ["cocktail"],
":coffee:" : ["coffee"],
":computer:" : ["computer"],
":confetti_ball:" : ["confetti ball"],
":cookie:" : ["cookie"],
":corn:" : ["corn"],
":credit_card:" : ["credit card"],
":crown:" : ["crown"],
":crystal_ball:" : ["crystal ball"],
":curry:" : ["curry"],
":custard:" : ["custard"],
":dango:" : ["dango"],
":dart:" : ["dart"],
":date:" : ["date"],
":diamonds:" : ["diamonds"],
":dollar:" : ["dollar"],
":door:" : ["door"],
":doughnut:" : ["doughnut"],
":dress:" : ["dress"],
":dvd:" : ["dvd"],
":e-mail:" : ["e-mail"],
":egg:" : ["egg"],
":eggplant:" : ["eggplant"],
":electric_plug:" : ["electric plug"],
":email, :envelope:" : ["email", "envelope"],
":euro:" : ["euro"],
":eyeglasses:" : ["eyeglasses"],
":fax:" : ["fax"],
":file_folder:" : ["file folder"],
":fish_cake:" : ["fish cake"],
":fishing_pole_and_fish:" : ["fishing pole and fish"],
":flashlight:" : ["flashlight"],
":floppy_disk:" : ["floppy disk"],
":flower_playing_cards:" : ["flower playing cards"],
":football:" : ["football"],
":fork_and_knife:" : ["fork and knife"],
":fried_shrimp:" : ["fried shrimp"],
":fries:" : ["fries"],
":game_die:" : ["game die"],
":gem:" : ["gem"],
":gift:" : ["gift"],
":golf:" : ["golf"],
":grapes:" : ["grapes"],
":green_apple:" : ["green apple"],
":green_book:" : ["green book"],
":guitar:" : ["guitar"],
":gun:" : ["gun"],
":hamburger:" : ["hamburger"],
":hammer:" : ["hammer"],
":handbag:" : ["handbag"],
":headphones:" : ["headphones"],
":hearts:" : ["hearts"],
":high_brightness:" : ["high brightness"],
":high_heel:" : ["high heel"],
":hocho:" : ["hocho"],
":honey_pot:" : ["honey pot"],
":horse_racing:" : ["horse racing"],
":hourglass:" : ["hourglass"],
":hourglass_flowing_sand:" : ["hourglass flowing sand"],
":ice_cream:" : ["ice cream"],
":icecream:" : ["icecream"],
":inbox_tray:" : ["inbox tray"],
":incoming_envelope:" : ["incoming envelope"],
":iphone:" : ["iphone"],
":jeans:" : ["jeans"],
":key:" : ["key"],
":kimono:" : ["kimono"],
":ledger:" : ["ledger"],
":lemon:" : ["lemon"],
":lipstick:" : ["lipstick"],
":lock:" : ["lock"],
":lock_with_ink_pen:" : ["lock with ink pen"],
":lollipop:" : ["lollipop"],
":loop:" : ["loop"],
":loudspeaker:" : ["loudspeaker"],
":low_brightness:" : ["low brightness"],
":mag:" : ["mag"],
":mag_right:" : ["mag right"],
":mahjong:" : ["mahjong"],
":mailbox:" : ["mailbox"],
":mailbox_closed:" : ["mailbox closed"],
":mailbox_with_mail:" : ["mailbox with mail"],
":mailbox_with_no_mail:" : ["mailbox with no mail"],
":mans_shoe, :shoe:" : ["mans shoe, :shoe"],
":meat_on_bone:" : ["meat on bone"],
":mega:" : ["mega"],
":melon:" : ["melon"],
":memo, :pencil:" : ["memo, :pencil"],
":microphone:" : ["microphone"],
":microscope:" : ["microscope"],
":minidisc:" : ["minidisc"],
":money_with_wings:" : ["money with wings"],
":moneybag:" : ["moneybag"],
":mountain_bicyclist:" : ["mountain bicyclist"],
":movie_camera:" : ["movie camera"],
":musical_keyboard:" : ["musical keyboard"],
":musical_score:" : ["musical score"],
":mute:" : ["mute"],
":name_badge:" : ["name badge"],
":necktie:" : ["necktie"],
":newspaper:" : ["newspaper"],
":no_bell:" : ["no bell"],
":notebook:" : ["notebook"],
":notebook_with_decorative_cover:" : ["notebook with decorative cover"],
":nut_and_bolt:" : ["nut and bolt"],
":oden:" : ["oden"],
":open_file_folder:" : ["open file folder"],
":orange_book:" : ["orange book"],
":outbox_tray:" : ["outbox tray"],
":page_facing_up:" : ["page facing up"],
":page_with_curl:" : ["page with curl"],
":pager:" : ["pager"],
":paperclip:" : ["paperclip"],
":peach:" : ["peach"],
":pear:" : ["pear"],
":pencil2:" : ["pencil2"],
":phone, :telephone:" : ["phone, :telephone"],
":pill:" : ["pill"],
":pineapple:" : ["pineapple"],
":pizza:" : ["pizza"],
":postal_horn:" : ["postal horn"],
":postbox:" : ["postbox"],
":pouch:" : ["pouch"],
":poultry_leg:" : ["poultry leg"],
":pound:" : ["pound"],
":purse:" : ["purse"],
":pushpin:" : ["pushpin"],
":radio:" : ["radio"],
":ramen:" : ["ramen"],
":ribbon:" : ["ribbon"],
":rice:" : ["rice"],
":rice_ball:" : ["rice ball"],
":rice_cracker:" : ["rice cracker"],
":ring:" : ["ring"],
":rugby_football:" : ["rugby football"],
":running_shirt_with_sash:" : ["running shirt with sash"],
":sake:" : ["sake"],
":sandal:" : ["sandal"],
":satellite:" : ["satellite"],
":saxophone:" : ["saxophone"],
":scissors:" : ["scissors"],
":scroll:" : ["scroll"],
":seat:" : ["seat"],
":shaved_ice:" : ["shaved ice"],
":shirt, :tshirt:" : ["shirt, :tshirt"],
":shower:" : ["shower"],
":ski:" : ["ski"],
":smoking:" : ["smoking"],
":snowboarder:" : ["snowboarder"],
":soccer:" : ["soccer"],
":sound:" : ["sound"],
":space_invader:" : ["space invader"],
":spades:" : ["spades"],
":spaghetti:" : ["spaghetti"],
":speaker:" : ["speaker"],
":stew:" : ["stew"],
":straight_ruler:" : ["straight ruler"],
":strawberry:" : ["strawberry"],
":surfer:" : ["surfer"],
":sushi:" : ["sushi"],
":sweet_potato:" : ["sweet potato"],
":swimmer:" : ["swimmer"],
":syringe:" : ["syringe"],
":tada:" : ["tada"],
":tanabata_tree:" : ["tanabata tree"],
":tangerine:" : ["tangerine"],
":tea:" : ["tea"],
":telephone_receiver:" : ["telephone receiver"],
":telescope:" : ["telescope"],
":tennis:" : ["tennis"],
":toilet:" : ["toilet"],
":tomato:" : ["tomato"],
":tophat:" : ["tophat"],
":triangular_ruler:" : ["triangular ruler"],
":trophy:" : ["trophy"],
":tropical_drink:" : ["tropical drink"],
":trumpet:" : ["trumpet"],
":tv:" : ["tv"],
":unlock:" : ["unlock"],
":vhs:" : ["vhs"],
":video_camera:" : ["video camera"],
":video_game:" : ["video game"],
":violin:" : ["violin"],
":watch:" : ["watch"],
":watermelon:" : ["watermelon"],
":wine_glass:" : ["wine glass"],
":womans_clothes:" : ["womans clothes"],
":womans_hat:" : ["womans hat"],
":wrench:" : ["wrench"],
":yen:" : ["yen"],
":smile:" : ["smile","SMILING FACE WITH OPEN MOUTH AND SMILING EYES"],
":laughing:" : ["laughing","SMILING FACE WITH OPEN MOUTH AND TIGHTLY-CLOSED EYES"],
":blush:" : ["blush","SMILING FACE WITH SMILING EYES"],
":smiley:" : ["smiley","SMILING FACE WITH OPEN MOUTH"],
":relaxed:" : ["relaxed","WHITE SMILING FACE"],
":smirk:" : ["smirk","SMIRKING FACE"],
":heart_eyes:" : ["heart eyes","SMILING FACE WITH HEART-SHAPED EYES"],
":kissing_heart:" : ["kissing heart","FACE THROWING KISS"],
":kissing_closed_eyes:" : ["kissing closed eyes","KISSING FACE WITH CLOSED EYES"],
":flushed:" : ["flushed","FLUSHED FACE"],
":relieved:" : ["relieved","DISAPPOINTED BUT RELIEVED FACE"],
":satisfied:" : ["satisfied","RELIEVED FACE"],
":grin:" : ["grin","GRINNING FACE WITH SMILING EYES"],
":wink:" : ["wink","WINKING FACE"],
":stuck_out_tongue_winking_eye, :wink2:" : ["stuck out tongue winking eye, :wink2","FACE WITH STUCK OUT TONGUE AND WINKING EYE","kidding", "not serious"], 
":stuck_out_tongue_closed_eyes:" : ["stuck out tongue closed eyes","FACE WITH STUCK-OUT TONGUE AND TIGHTLY-CLOSED EYES","kidding", "not serious"],
":grinning:" : ["grinning","GRINNING FACE"],
":kissing:" : ["kissing","KISSING FACE"],
":kissing_smiling_eyes:" : ["kissing smiling eyes","KISSING FACE WITH SMILING EYES"],
":stuck_out_tongue:" : ["stuck out tongue","FACE WITH STUCK-OUT TONGUE"],
":sleeping:" : ["sleeping","SLEEPING FACE"],
":worried:" : ["worried","WORRIED FACE"],
":frowning:" : ["frowning","FROWNING FACE WITH OPEN MOUTH"],
":anguished:" : ["anguished","ANGUISHED FACE"],
":open_mouth:" : ["open mouth","FACE WITH OPEN MOUTH"],
":grimacing:" : ["grimacing","GRIMACING FACE"],
":confused:" : ["confused","CONFUSED FACE"],
":hushed:" : ["hushed","HUSHED FACE"],
":expressionless:" : ["expressionless","EXPRESSIONLESS FACE"],
":unamused:" : ["unamused","UNAMUSED FACE"],
":sweat_smile:" : ["sweat smile","SMILING FACE WITH OPEN MOUTH AND COLD SWEAT"],
":sweat:" : ["sweat","FACE WITH COLD SWEAT"],
":weary:" : ["weary","WEARY FACE"],
":pensive:" : ["pensive","PENSIVE FACE"],
":disappointed:" : ["disappointed","DISAPPOINTED FACE"],
":confounded:" : ["confounded","CONFOUNDED FACE"],
":fearful:" : ["fearful","FEARFUL FACE"],
":cold_sweat:" : ["cold sweat","FACE WITH OPEN MOUTH AND COLD SWEAT"],
":persevere:" : ["persevere","PERSEVERING FACE"],
":cry:" : ["cry","CRYING FACE"],
":sob:" : ["sob","LOUDLY CRYING FACE"],
":joy:" : ["joy","FACE WITH TEARS OF JOY"],
":astonished:" : ["astonished","ASTONISHED FACE"],
":scream:" : ["scream","FACE SCREAMING IN FEAR"],
":tired_face:" : ["tired face"],
":angry:" : ["angry","ANGRY FACE"],
":rage:" : ["rage","POUTING FACE"],
":triumph:" : ["triumph","FACE WITH LOOK OF TRIUMPH"],
":sleepy:" : ["sleepy","SLEEPY FACE"],
":yum:" : ["yum","FACE SAVOURING DELICIOUS FOOD"],
":mask:" : ["mask","FACE WITH MEDICAL MASK"],
":sunglasses:" : ["sunglasses","SMILING FACE WITH SUNGLASSES"],
":dizzy_face:" : ["dizzy face"],
":imp:" : ["imp"],
":smiling_imp:" : ["smiling imp","SMILING FACE WITH HORNS"],
":neutral_face:" : ["neutral face"],
":no_mouth:" : ["no mouth","FACE WITHOUT MOUTH"],
":innocent:" : ["innocent","SMILING FACE WITH HALO"],
":alien:" : ["alien","EXTRATERRESTRIAL ALIEN"],
":yellow_heart:" : ["yellow heart"],
":blue_heart:" : ["blue heart"],
":purple_heart:" : ["purple heart"],
":heart:" : ["heart","HEAVY BLACK HEART"],
":green_heart:" : ["green heart"],
":broken_heart:" : ["broken heart"],
":heartbeat:" : ["heartbeat","BEATING HEART"],
":heartpulse:" : ["heartpulse","GROWING HEART"],
":two_hearts:" : ["two hearts"],
":revolving_hearts:" : ["revolving hearts"],
":cupid:" : ["cupid","HEART WITH ARROW"],
":sparkling_heart:" : ["sparkling heart"],
":sparkles:" : ["sparkles"],
":star:" : ["star","WHITE MEDIUM STAR"],
":star2:" : ["star2","GLOWING STAR"],
":dizzy:" : ["dizzy","DIZZY SYMBOL","circling stars", "squeans"], 
":boom, :collision:" : ["boom, :collision","COLLISION SYMBOL"],
":anger:" : ["anger","ANGER SYMBOL"],
":exclamation:" : ["exclamation","HEAVY EXCLAMATION MARK SYMBOL"],
":question:" : ["question","BLACK QUESTION MARK ORNAMENT"],
":grey_exclamation:" : ["grey exclamation","WHITE EXCLAMATION MARK ORNAMENT"],
":grey_question:" : ["grey question","WHITE QUESTION MARK ORNAMENT"],
":zzz:" : ["zzz","SLEEPING SYMBOL"],
":dash:" : ["dash","DASH SYMBOL","running dash", "briffits"],
":sweat_drops:" : ["sweat drops","SPLASHING SWEAT SYMBOL","plewds"],
":notes:" : ["notes","MULTIPLE MUSICAL NOTES","dancing notes", "mood", "melody"],
":musical_note:" : ["musical note","music", "good mood"],
":fire:" : ["fire","FIRE"],
":hankey, :poop, :shit:" : ["hankey, :poop, :shit","PILE OF POO","dog dirt"],
":thumbsup:" : ["thumbsup","THUMBS UP SIGN"],
":thumbsdown:" : ["thumbsdown","THUMBS DOWN SIGN"],
":ok_hand:" : ["ok hand","OK HAND SIGN"],
":punch, :facepunch:" : ["punch, :facepunch","FISTED HAND SIGN","punch"],
":fist:" : ["fist","RAISED FIST"],
":v:" : ["v","VICTORY HAND"],
":wave:" : ["wave","WAVING HAND SIGN"],
":hand:" : ["hand","RAISED HAND"],
":open_hands:" : ["open hands","OPEN HANDS SIGN"],
":point_up:" : ["point up","WHITE UP POINTING INDEX"],
":point_down:" : ["point down","WHITE DOWN POINTING BACKHAND INDEX"],
":point_left:" : ["point left","WHITE LEFT POINTING BACKHAND INDEX"],
":point_right:" : ["point right","WHITE RIGHT POINTING BACKHAND INDEX"],
":raised_hands:" : ["raised hands","PERSON RAISING BOTH HANDS IN CELEBRATION","banzai"], 
":pray:" : ["pray","PERSON WITH FOLDED HANDS","sorry","regret","pleading"], 
":point_up_2:" : ["point up 2","WHITE UP POINTING BACKHAND INDEX"],
":clap:" : ["clap","CLAPPING HANDS SIGN"],
":muscle:" : ["muscle","FLEXED BICEPS","strong", "muscle"],
":walking:" : ["walking","PEDESTRIAN"],
":runner, :running:" : ["runner, :running"],
":couple:" : ["couple","MAN AND WOMAN HOLDING HANDS"],
":family:" : ["family"],
":two_men_holding_hands:" : ["two men holding hands"],
":two_women_holding_hands:" : ["two women holding hands"],
":dancer:" : ["dancer"],
":dancers:" : ["dancers","WOMAN WITH BUNNY EARS"],
":ok_woman:" : ["ok woman","FACE WITH OK GESTURE"],
":no_good:" : ["no good","FACE WITH NO GOOD GESTURE"],
":information_desk_person:" : ["information desk person"],
":raised_hand:" : ["raised hand","HAPPY PERSON RAISING ONE HAND"],
":bride_with_veil:" : ["bride with veil"],
":person_with_pouting_face:" : ["person with pouting face"],
":person_frowning:" : ["person frowning"],
":bow:" : ["bow","PERSON BOWING DEEPLY"],
":couplekiss:" : ["couplekiss","KISS","kissing"],
":couple_with_heart:" : ["couple with heart"],
":massage:" : ["massage","FACE MASSAGE"],
":haircut:" : ["haircut"], 
":nail_care:" : ["nail care","NAIL POLISH","manicure","nail"],
":boy:" : ["boy"],
":girl:" : ["girl"],
":woman:" : ["woman"],
":man:" : ["man"],
":baby:" : ["baby"],
":older_woman:" : ["older woman"],
":older_man:" : ["older man"],
":person_with_blond_hair:" : ["person with blond hair"],
":man_with_gua_pi_mao:" : ["man with gua pi mao"],
":man_with_turban:" : ["man with turban"],
":construction_worker:" : ["construction worker"],
":cop:" : ["cop","POLICE OFFICER"],
":angel:" : ["angel","BABY ANGEL"],
":princess:" : ["princess"],
":smiley_cat:" : ["smiley cat","SMILING CAT FACE WITH OPEN MOUTH"],
":smile_cat:" : ["smile cat","GRINNING CAT FACE WITH SMILING EYES"],
":heart_eyes_cat:" : ["heart eyes cat","SMILING CAT FACE WITH HEART-SHAPED EYES"],
":kissing_cat:" : ["kissing cat","KISSING CAT FACE WITH CLOSED EYES"],
":smirk_cat:" : ["smirk cat","CAT FACE WITH WRY SMILE"],
":scream_cat:" : ["scream cat","WEARY CAT FACE"],
":crying_cat_face:" : ["crying cat face","CRYING CAT FACE"],
":joy_cat:" : ["joy cat","CAT FACE WITH TEARS OF JOY"],
":pouting_cat:" : ["pouting cat","POUTING CAT FACE"],
":japanese_ogre:" : ["japanese ogre"],
":japanese_goblin:" : ["japanese goblin"],
":see_no_evil:" : ["see no evil","SEE-NO-EVIL MONKEY"],
":hear_no_evil:" : ["hear no evil","HEAR-NO-EVIL MONKEY"],
":speak_no_evil:" : ["speak no evil","SPEAK-NO-EVIL MONKEY"],
":guardsman:" : ["guardsman"],
":skull:" : ["skull"],
":feet:" : ["feet","FOOTPRINTS"],
":lips:" : ["lips","MOUTH"],
":kiss:" : ["kiss","KISS MARK","lips"],
":droplet:" : ["droplet","water","sweat"], 
":ear:" : ["ear"],
":eyes:" : ["eyes"],
":nose:" : ["nose"],
":tongue:" : ["tongue"],
":love_letter:" : ["love letter"],
":bust_in_silhouette:" : ["bust in silhouette","guest account", "guest"],
":busts_in_silhouette:" : ["busts in silhouette","accounts", "account"],
":speech_balloon:" : ["speech balloon","comic book ","conversation bubble", "comic", "comics", "conversation", "bubble"],
":thought_balloon:" : ["thought balloon"],
":100:" : ["100"],
":1234:" : ["1234"],
":a:" : ["a"],
":ab:" : ["ab"],
":abc:" : ["abc"],
":abcd:" : ["abcd"],
":accept:" : ["accept"],
":aquarius:" : ["aquarius"],
":aries:" : ["aries"],
":arrow_backward:" : ["arrow backward"],
":arrow_double_down:" : ["arrow double down"],
":arrow_double_up:" : ["arrow double up"],
":arrow_down:" : ["arrow down"],
":arrow_down_small:" : ["arrow down small"],
":arrow_forward:" : ["arrow forward"],
":arrow_heading_down:" : ["arrow heading down"],
":arrow_heading_up:" : ["arrow heading up"],
":arrow_left:" : ["arrow left"],
":arrow_lower_left:" : ["arrow lower left"],
":arrow_lower_right:" : ["arrow lower right"],
":arrow_right:" : ["arrow right"],
":arrow_right_hook:" : ["arrow right hook"],
":arrow_up:" : ["arrow up"],
":arrow_up_down:" : ["arrow up down"],
":arrow_up_small:" : ["arrow up small"],
":arrow_upper_left:" : ["arrow upper left"],
":arrow_upper_right:" : ["arrow upper right"],
":arrows_clockwise:" : ["arrows clockwise"],
":arrows_counterclockwise:" : ["arrows counterclockwise"],
":b:" : ["b"],
":baby_symbol:" : ["baby symbol"],
":baggage_claim:" : ["baggage claim"],
":ballot_box_with_check:" : ["ballot box with check"],
":bangbang:" : ["bangbang"],
":black_circle:" : ["black circle"],
":black_square_button:" : ["black square button"],
":cancer:" : ["cancer"],
":capital_abcd:" : ["capital abcd"],
":capricorn:" : ["capricorn"],
":chart:" : ["chart"],
":children_crossing:" : ["children crossing"],
":cinema:" : ["cinema"],
":cl:" : ["cl"],
":clock1:" : ["clock1"],
":clock10:" : ["clock10"],
":clock1030:" : ["clock1030"],
":clock11:" : ["clock11"],
":clock1130:" : ["clock1130"],
":clock12:" : ["clock12"],
":clock1230:" : ["clock1230"],
":clock130:" : ["clock130"],
":clock2:" : ["clock2"],
":clock230:" : ["clock230"],
":clock3:" : ["clock3"],
":clock330:" : ["clock330"],
":clock4:" : ["clock4"],
":clock430:" : ["clock430"],
":clock5:" : ["clock5"],
":clock530:" : ["clock530"],
":clock6:" : ["clock6"],
":clock630:" : ["clock630"],
":clock7:" : ["clock7"],
":clock730:" : ["clock730"],
":clock8:" : ["clock8"],
":clock830:" : ["clock830"],
":clock9:" : ["clock9"],
":clock930:" : ["clock930"],
":congratulations:" : ["congratulations"],
":cool:" : ["cool"],
":copyright:" : ["copyright"],
":curly_loop:" : ["curly loop"],
":currency_exchange:" : ["currency exchange"],
":customs:" : ["customs"],
":diamond_shape_with_a_dot_inside:" : ["diamond shape with a dot inside"],
":do_not_litter:" : ["do not litter"],
":eight:" : ["eight"],
":eight_pointed_black_star:" : ["eight pointed black star"],
":eight_spoked_asterisk:" : ["eight spoked asterisk"],
":end:" : ["end"],
":fast_forward:" : ["fast forward"],
":five:" : ["five"],
":four:" : ["four"],
":free:" : ["free"],
":gemini:" : ["gemini"],
":hash:" : ["hash"],
":heart_decoration:" : ["heart decoration"],
":heavy_check_mark:" : ["heavy check mark"],
":heavy_division_sign:" : ["heavy division sign"],
":heavy_dollar_sign:" : ["heavy dollar sign"],
":heavy_minus_sign:" : ["heavy minus sign"],
":heavy_multiplication_x:" : ["heavy multiplication x"],
":heavy_plus_sign:" : ["heavy plus sign"],
":id:" : ["id"],
":ideograph_advantage:" : ["ideograph advantage"],
":information_source:" : ["information source"],
":interrobang:" : ["interrobang"],
":keycap_ten:" : ["keycap ten"],
":koko:" : ["koko"],
":large_blue_circle:" : ["large blue circle"],
":large_blue_diamond:" : ["large blue diamond"],
":large_orange_diamond:" : ["large orange diamond"],
":left_luggage:" : ["left luggage"],
":left_right_arrow:" : ["left right arrow"],
":leftwards_arrow_with_hook:" : ["leftwards arrow with hook"],
":leo:" : ["leo"],
":libra:" : ["libra"],
":link:" : ["link"],
":m:" : ["m"],
":mens:" : ["mens"],
":metro:" : ["metro"],
":mobile_phone_off:" : ["mobile phone off"],
":negative_squared_cross_mark:" : ["negative squared cross mark"],
":new:" : ["new"],
":ng:" : ["ng"],
":nine:" : ["nine"],
":no_bicycles:" : ["no bicycles"],
":no_entry:" : ["no entry"],
":no_entry_sign:" : ["no entry sign"],
":no_mobile_phones:" : ["no mobile phones"],
":no_pedestrians:" : ["no pedestrians"],
":no_smoking:" : ["no smoking"],
":non-potable_water:" : ["non-potable_water"],
":o:" : ["o"],
":o2:" : ["o2"],
":ok:" : ["ok"],
":on:" : ["on"],
":one:" : ["one"],
":ophiuchus:" : ["ophiuchus"],
":parking:" : ["parking"],
":part_alternation_mark:" : ["part alternation mark"],
":passport_control:" : ["passport control"],
":pisces:" : ["pisces"],
":potable_water:" : ["potable water"],
":put_litter_in_its_place:" : ["put litter in its place"],
":radio_button:" : ["radio button"],
":recycle:" : ["recycle"],
":red_circle:" : ["red circle"],
":registered:" : ["registered"],
":repeat:" : ["repeat"],
":repeat_one:" : ["repeat one"],
":restroom:" : ["restroom"],
":rewind:" : ["rewind"],
":sa:" : ["sa"],
":sagittarius:" : ["sagittarius"],
":scorpius:" : ["scorpius"],
":secret:" : ["secret"],
":seven:" : ["seven"],
":signal_strength:" : ["signal strength"],
":six:" : ["six"],
":six_pointed_star:" : ["six pointed star"],
":small_blue_diamond:" : ["small blue diamond"],
":small_orange_diamond:" : ["small orange diamond"],
":small_red_triangle:" : ["small red triangle"],
":small_red_triangle_down:" : ["small red triangle down"],
":soon:" : ["soon"],
":sos:" : ["sos"],
":symbols:" : ["symbols"],
":taurus:" : ["taurus"],
":three:" : ["three"],
":tm:" : ["tm"],
":top:" : ["top"],
":trident:" : ["trident"],
":twisted_rightwards_arrows:" : ["twisted rightwards arrows"],
":two:" : ["two"],
":u5272:" : ["u5272"],
":u5408:" : ["u5408"],
":u55b6:" : ["u55b6"],
":u6307:" : ["u6307"],
":u6708:" : ["u6708"],
":u6709:" : ["u6709"],
":u6e80:" : ["u6e80"],
":u7121:" : ["u7121"],
":u7533:" : ["u7533"],
":u7981:" : ["u7981"],
":u7a7a:" : ["u7a7a"],
":underage:" : ["underage"],
":up:" : ["up"],
":vibration_mode:" : ["vibration mode"],
":virgo:" : ["virgo"],
":vs:" : ["vs"],
":wavy_dash:" : ["wavy dash"],
":wc:" : ["wc"],
":wheelchair:" : ["wheelchair"],
":white_check_mark:" : ["white check mark"],
":white_circle:" : ["white circle"],
":white_flower:" : ["white flower"],
":white_square_button:" : ["white square button"],
":womens:" : ["womens"],
":x:" : ["x"],
":zero:" : ["zero"]}
